{
    "swagger": "2.0",
    "info": {
        "description": "Swagger social media",
        "title": "Demo Swagger API",
        "contact": {},
        "version": "1.0"
    },
    "host": "localhost:8080",
    "paths": {
        "/comments/{id}": {
            "put": {
                "description": "Cập nhật nội dung bình luận theo ID",
                "consumes": [
                    "application/json"
                ],
                "produces": [
                    "application/json"
                ],
                "tags": [
                    "comments"
                ],
                "summary": "Cập nhật bình luận",
                "parameters": [
                    {
                        "type": "integer",
                        "description": "Comment ID",
                        "name": "id",
                        "in": "path",
                        "required": true
                    },
                    {
                        "description": "Comment",
                        "name": "comment",
                        "in": "body",
                        "required": true,
                        "schema": {
                            "$ref": "#/definitions/models.Comment"
                        }
                    }
                ],
                "responses": {
                    "200": {
                        "description": "OK",
                        "schema": {
                            "$ref": "#/definitions/models.MessageResponse"
                        }
                    },
                    "404": {
                        "description": "Not Found",
                        "schema": {
                            "$ref": "#/definitions/models.ErrorResponse"
                        }
                    },
                    "500": {
                        "description": "Internal Server Error",
                        "schema": {
                            "$ref": "#/definitions/models.ErrorResponse"
                        }
                    }
                }
            },
            "delete": {
                "description": "Xoá bình luận theo ID",
                "tags": [
                    "comments"
                ],
                "summary": "Xoá bình luận",
                "parameters": [
                    {
                        "type": "integer",
                        "description": "Comment ID",
                        "name": "id",
                        "in": "path",
                        "required": true
                    }
                ],
                "responses": {
                    "200": {
                        "description": "OK",
                        "schema": {
                            "$ref": "#/definitions/models.MessageResponse"
                        }
                    },
                    "404": {
                        "description": "Not Found",
                        "schema": {
                            "$ref": "#/definitions/models.ErrorResponse"
                        }
                    },
                    "500": {
                        "description": "Internal Server Error",
                        "schema": {
                            "$ref": "#/definitions/models.ErrorResponse"
                        }
                    }
                }
            }
        },
        "/posts": {
            "get": {
                "description": "Trả về danh sách tất cả bài viết",
                "produces": [
                    "application/json"
                ],
                "tags": [
                    "posts"
                ],
                "summary": "Lấy danh sách bài viết",
                "responses": {
                    "200": {
                        "description": "OK",
                        "schema": {
                            "type": "array",
                            "items": {
                                "$ref": "#/definitions/models.Post"
                            }
                        }
                    }
                }
            },
            "post": {
                "description": "Tạo một bài viết",
                "consumes": [
                    "application/json"
                ],
                "produces": [
                    "application/json"
                ],
                "tags": [
                    "posts"
                ],
                "summary": "Tạo bài viết mới",
                "parameters": [
                    {
                        "description": "Post",
                        "name": "post",
                        "in": "body",
                        "required": true,
                        "schema": {
                            "$ref": "#/definitions/models.Post"
                        }
                    }
                ],
                "responses": {
                    "200": {
                        "description": "OK",
                        "schema": {
                            "$ref": "#/definitions/models.MessageResponse"
                        }
                    },
                    "404": {
                        "description": "Not Found",
                        "schema": {
                            "$ref": "#/definitions/models.ErrorResponse"
                        }
                    },
                    "500": {
                        "description": "Internal Server Error",
                        "schema": {
                            "$ref": "#/definitions/models.ErrorResponse"
                        }
                    }
                }
            }
        },
        "/posts/{id}": {
            "get": {
                "description": "Trả về chi tiết bài viết theo ID",
                "produces": [
                    "application/json"
                ],
                "tags": [
                    "posts"
                ],
                "summary": "Lấy chi tiết bài viết",
                "parameters": [
                    {
                        "type": "integer",
                        "description": "Post ID",
                        "name": "id",
                        "in": "path",
                        "required": true
                    }
                ],
                "responses": {
                    "200": {
                        "description": "OK",
                        "schema": {
                            "$ref": "#/definitions/models.MessageResponse"
                        }
                    },
                    "404": {
                        "description": "Not Found",
                        "schema": {
                            "$ref": "#/definitions/models.ErrorResponse"
                        }
                    },
                    "500": {
                        "description": "Internal Server Error",
                        "schema": {
                            "$ref": "#/definitions/models.ErrorResponse"
                        }
                    }
                }
            },
            "put": {
                "description": "Cập nhật bài viết theo ID",
                "consumes": [
                    "application/json"
                ],
                "produces": [
                    "application/json"
                ],
                "tags": [
                    "posts"
                ],
                "summary": "Cập nhật bài viết",
                "parameters": [
                    {
                        "type": "integer",
                        "description": "Post ID",
                        "name": "id",
                        "in": "path",
                        "required": true
                    },
                    {
                        "description": "Post",
                        "name": "post",
                        "in": "body",
                        "required": true,
                        "schema": {
                            "$ref": "#/definitions/models.Post"
                        }
                    }
                ],
                "responses": {
                    "200": {
                        "description": "OK",
                        "schema": {
                            "$ref": "#/definitions/models.MessageResponse"
                        }
                    },
                    "404": {
                        "description": "Not Found",
                        "schema": {
                            "$ref": "#/definitions/models.ErrorResponse"
                        }
                    },
                    "500": {
                        "description": "Internal Server Error",
                        "schema": {
                            "$ref": "#/definitions/models.ErrorResponse"
                        }
                    }
                }
            },
            "delete": {
                "description": "Xoá bài viết theo ID",
                "tags": [
                    "posts"
                ],
                "summary": "Xoá bài viết",
                "parameters": [
                    {
                        "type": "integer",
                        "description": "Post ID",
                        "name": "id",
                        "in": "path",
                        "required": true
                    }
                ],
                "responses": {
                    "200": {
                        "description": "OK",
                        "schema": {
                            "$ref": "#/definitions/models.MessageResponse"
                        }
                    },
                    "404": {
                        "description": "Not Found",
                        "schema": {
                            "$ref": "#/definitions/models.ErrorResponse"
                        }
                    },
                    "500": {
                        "description": "Internal Server Error",
                        "schema": {
                            "$ref": "#/definitions/models.ErrorResponse"
                        }
                    }
                }
            }
        },
        "/posts/{post_id}/comments": {
            "get": {
                "description": "Trả về tất cả bình luận thuộc về một bài viết theo post_id",
                "produces": [
                    "application/json"
                ],
                "tags": [
                    "comments"
                ],
                "summary": "Lấy danh sách bình luận theo bài viết",
                "parameters": [
                    {
                        "type": "integer",
                        "description": "Post ID",
                        "name": "post_id",
                        "in": "path",
                        "required": true
                    }
                ],
                "responses": {
                    "200": {
                        "description": "OK",
                        "schema": {
                            "type": "array",
                            "items": {
                                "$ref": "#/definitions/models.Comment"
                            }
                        }
                    },
                    "404": {
                        "description": "Not Found",
                        "schema": {
                            "$ref": "#/definitions/models.ErrorResponse"
                        }
                    },
                    "500": {
                        "description": "Internal Server Error",
                        "schema": {
                            "$ref": "#/definitions/models.ErrorResponse"
                        }
                    }
                }
            },
            "post": {
                "description": "Tạo bình luận mới cho bài viết",
                "consumes": [
                    "application/json"
                ],
                "produces": [
                    "application/json"
                ],
                "tags": [
                    "comments"
                ],
                "summary": "Tạo bình luận",
                "parameters": [
                    {
                        "description": "Comment",
                        "name": "comment",
                        "in": "body",
                        "required": true,
                        "schema": {
                            "$ref": "#/definitions/models.Comment"
                        }
                    }
                ],
                "responses": {
                    "200": {
                        "description": "OK",
                        "schema": {
                            "$ref": "#/definitions/models.MessageResponse"
                        }
                    },
                    "404": {
                        "description": "Not Found",
                        "schema": {
                            "$ref": "#/definitions/models.ErrorResponse"
                        }
                    },
                    "500": {
                        "description": "Internal Server Error",
                        "schema": {
                            "$ref": "#/definitions/models.ErrorResponse"
                        }
                    }
                }
            }
        }
    },
    "definitions": {
        "models.Comment": {
            "type": "object",
            "properties": {
                "content": {
                    "type": "string",
                    "example": "Nice post!"
                },
                "created_at": {
                    "type": "string"
                },
                "id": {
                    "type": "integer",
                    "example": 1
                },
                "post_id": {
                    "type": "string"
                }
            }
        },
        "models.ErrorResponse": {
            "type": "object",
            "properties": {
                "error": {
                    "type": "string",
                    "example": "Có lỗi xảy ra"
                }
            }
        },
        "models.MessageResponse": {
            "type": "object",
            "properties": {
                "message": {
                    "type": "string",
                    "example": "Thành công"
                }
            }
        },
        "models.Post": {
            "type": "object",
            "properties": {
                "comments": {
                    "type": "string"
                },
                "content": {
                    "type": "string",
                    "example": "Content goes here"
                },
                "created_at": {
                    "type": "string"
                },
                "id": {
                    "type": "integer",
                    "example": 1
                },
                "title": {
                    "type": "string",
                    "example": "My Post"
                }
            }
        }
    }
}